metamock/__init__.py
metamock/__main__.py
metamock/api_manager.py
metamock/app.py
metamock/custom_data_generation.py
metamock/faker_data.py
metamock/klass_classifications_data.py
metamock/logger.py
metamock/logger_decorator.py
metamock/py.typed
metamock/snr_manager.py
metamock/utils.py
metamock/vardok_data.py
ssb_metamock-0.1.0.dist-info/LICENSE
ssb_metamock-0.1.0.dist-info/METADATA
ssb_metamock-0.1.0.dist-info/WHEEL
ssb_metamock-0.1.0.dist-info/entry_points.txt
ssb_metamock-0.1.0.dist-info/RECORD
