Metadata-Version: 2.1
Name: ssb-metamock
Version: 0.1.0
Summary: Generate synthetic data from datadoc metadata
Home-page: https://github.com/statisticsnorway/metamock
License: MIT
Author: Amund Lågbu
Author-email: mgb@ssb.no
Requires-Python: >=3.10,<3.13
Classifier: Development Status :: 2 - Pre-Alpha
Classifier: License :: OSI Approved :: MIT License
Classifier: Programming Language :: Python :: 3
Classifier: Programming Language :: Python :: 3.10
Classifier: Programming Language :: Python :: 3.11
Requires-Dist: defusedxml (>=0.7.1,<0.8.0)
Requires-Dist: faker (>=19.3.1)
Requires-Dist: numpy (>=1.26.0)
Requires-Dist: pandas (>=1.5.3)
Requires-Dist: pydantic (<2)
Requires-Dist: requests (>=2.31.0)
Requires-Dist: ssb-datadoc-model (>=2.0.1)
Requires-Dist: ssb-klass-python (>=0.0.6)
Requires-Dist: xdg-base-dirs (>=6.0.1,<7.0.0)
Project-URL: Changelog, https://github.com/statisticsnorway/metamock/releases
Project-URL: Documentation, https://statisticsnorway.github.io/metamock
Project-URL: Repository, https://github.com/statisticsnorway/metamock
